{
  "id": "d24047bb-441a-4e88-ae69-6b2ecd8b3b20",
  "prevId": "35331493-a0b5-44a3-9067-0cc7e8ae0ccf",
  "version": "7",
  "dialect": "postgresql",
  "tables": {
    "public.account": {
      "name": "account",
      "schema": "",
      "columns": {
        "id": {
          "name": "id",
          "type": "text",
          "primaryKey": true,
          "notNull": true
        },
        "account_id": {
          "name": "account_id",
          "type": "text",
          "primaryKey": false,
          "notNull": true
        },
        "provider_id": {
          "name": "provider_id",
          "type": "text",
          "primaryKey": false,
          "notNull": true
        },
        "user_id": {
          "name": "user_id",
          "type": "text",
          "primaryKey": false,
          "notNull": true
        },
        "access_token": {
          "name": "access_token",
          "type": "text",
          "primaryKey": false,
          "notNull": false
        },
        "refresh_token": {
          "name": "refresh_token",
          "type": "text",
          "primaryKey": false,
          "notNull": false
        },
        "id_token": {
          "name": "id_token",
          "type": "text",
          "primaryKey": false,
          "notNull": false
        },
        "access_token_expires_at": {
          "name": "access_token_expires_at",
          "type": "timestamp",
          "primaryKey": false,
          "notNull": false
        },
        "refresh_token_expires_at": {
          "name": "refresh_token_expires_at",
          "type": "timestamp",
          "primaryKey": false,
          "notNull": false
        },
        "scope": {
          "name": "scope",
          "type": "text",
          "primaryKey": false,
          "notNull": false
        },
        "password": {
          "name": "password",
          "type": "text",
          "primaryKey": false,
          "notNull": false
        },
        "created_at": {
          "name": "created_at",
          "type": "timestamp",
          "primaryKey": false,
          "notNull": true
        },
        "updated_at": {
          "name": "updated_at",
          "type": "timestamp",
          "primaryKey": false,
          "notNull": true
        }
      },
      "indexes": {},
      "foreignKeys": {
        "account_user_id_user_id_fk": {
          "name": "account_user_id_user_id_fk",
          "tableFrom": "account",
          "tableTo": "user",
          "columnsFrom": [
            "user_id"
          ],
          "columnsTo": [
            "id"
          ],
          "onDelete": "cascade",
          "onUpdate": "no action"
        }
      },
      "compositePrimaryKeys": {},
      "uniqueConstraints": {},
      "policies": {},
      "checkConstraints": {},
      "isRLSEnabled": false
    },
    "public.session": {
      "name": "session",
      "schema": "",
      "columns": {
        "id": {
          "name": "id",
          "type": "text",
          "primaryKey": true,
          "notNull": true
        },
        "expires_at": {
          "name": "expires_at",
          "type": "timestamp",
          "primaryKey": false,
          "notNull": true
        },
        "token": {
          "name": "token",
          "type": "text",
          "primaryKey": false,
          "notNull": true
        },
        "created_at": {
          "name": "created_at",
          "type": "timestamp",
          "primaryKey": false,
          "notNull": true
        },
        "updated_at": {
          "name": "updated_at",
          "type": "timestamp",
          "primaryKey": false,
          "notNull": true
        },
        "ip_address": {
          "name": "ip_address",
          "type": "text",
          "primaryKey": false,
          "notNull": false
        },
        "user_agent": {
          "name": "user_agent",
          "type": "text",
          "primaryKey": false,
          "notNull": false
        },
        "user_id": {
          "name": "user_id",
          "type": "text",
          "primaryKey": false,
          "notNull": true
        }
      },
      "indexes": {},
      "foreignKeys": {
        "session_user_id_user_id_fk": {
          "name": "session_user_id_user_id_fk",
          "tableFrom": "session",
          "tableTo": "user",
          "columnsFrom": [
            "user_id"
          ],
          "columnsTo": [
            "id"
          ],
          "onDelete": "cascade",
          "onUpdate": "no action"
        }
      },
      "compositePrimaryKeys": {},
      "uniqueConstraints": {
        "session_token_unique": {
          "name": "session_token_unique",
          "nullsNotDistinct": false,
          "columns": [
            "token"
          ]
        }
      },
      "policies": {},
      "checkConstraints": {},
      "isRLSEnabled": false
    },
    "public.user": {
      "name": "user",
      "schema": "",
      "columns": {
        "id": {
          "name": "id",
          "type": "text",
          "primaryKey": true,
          "notNull": true
        },
        "name": {
          "name": "name",
          "type": "text",
          "primaryKey": false,
          "notNull": true
        },
        "email": {
          "name": "email",
          "type": "text",
          "primaryKey": false,
          "notNull": true
        },
        "email_verified": {
          "name": "email_verified",
          "type": "boolean",
          "primaryKey": false,
          "notNull": true
        },
        "image": {
          "name": "image",
          "type": "text",
          "primaryKey": false,
          "notNull": false
        },
        "display_name": {
          "name": "display_name",
          "type": "text",
          "primaryKey": false,
          "notNull": false,
          "default": "'Survivor'"
        },
        "is_admin": {
          "name": "is_admin",
          "type": "boolean",
          "primaryKey": false,
          "notNull": true
        },
        "created_at": {
          "name": "created_at",
          "type": "timestamp",
          "primaryKey": false,
          "notNull": true
        },
        "updated_at": {
          "name": "updated_at",
          "type": "timestamp",
          "primaryKey": false,
          "notNull": true
        }
      },
      "indexes": {},
      "foreignKeys": {},
      "compositePrimaryKeys": {},
      "uniqueConstraints": {
        "user_email_unique": {
          "name": "user_email_unique",
          "nullsNotDistinct": false,
          "columns": [
            "email"
          ]
        }
      },
      "policies": {},
      "checkConstraints": {},
      "isRLSEnabled": false
    },
    "public.user_stats": {
      "name": "user_stats",
      "schema": "",
      "columns": {
        "id": {
          "name": "id",
          "type": "text",
          "primaryKey": true,
          "notNull": true
        },
        "user_id": {
          "name": "user_id",
          "type": "text",
          "primaryKey": false,
          "notNull": true
        },
        "zombie_kills": {
          "name": "zombie_kills",
          "type": "integer",
          "primaryKey": false,
          "notNull": true,
          "default": 0
        },
        "experience": {
          "name": "experience",
          "type": "integer",
          "primaryKey": false,
          "notNull": true,
          "default": 0
        },
        "skill_allocations": {
          "name": "skill_allocations",
          "type": "jsonb",
          "primaryKey": false,
          "notNull": true,
          "default": "'{}'::jsonb"
        },
        "character_allocations": {
          "name": "character_allocations",
          "type": "jsonb",
          "primaryKey": false,
          "notNull": true,
          "default": "'{}'::jsonb"
        },
        "last_tile_x": {
          "name": "last_tile_x",
          "type": "integer",
          "primaryKey": false,
          "notNull": false
        },
        "last_tile_y": {
          "name": "last_tile_y",
          "type": "integer",
          "primaryKey": false,
          "notNull": false
        },
        "created_at": {
          "name": "created_at",
          "type": "timestamp",
          "primaryKey": false,
          "notNull": true
        },
        "updated_at": {
          "name": "updated_at",
          "type": "timestamp",
          "primaryKey": false,
          "notNull": true
        }
      },
      "indexes": {},
      "foreignKeys": {
        "user_stats_user_id_user_id_fk": {
          "name": "user_stats_user_id_user_id_fk",
          "tableFrom": "user_stats",
          "tableTo": "user",
          "columnsFrom": [
            "user_id"
          ],
          "columnsTo": [
            "id"
          ],
          "onDelete": "cascade",
          "onUpdate": "no action"
        }
      },
      "compositePrimaryKeys": {},
      "uniqueConstraints": {
        "user_stats_user_id_unique": {
          "name": "user_stats_user_id_unique",
          "nullsNotDistinct": false,
          "columns": [
            "user_id"
          ]
        }
      },
      "policies": {},
      "checkConstraints": {},
      "isRLSEnabled": false
    },
    "public.verification": {
      "name": "verification",
      "schema": "",
      "columns": {
        "id": {
          "name": "id",
          "type": "text",
          "primaryKey": true,
          "notNull": true
        },
        "identifier": {
          "name": "identifier",
          "type": "text",
          "primaryKey": false,
          "notNull": true
        },
        "value": {
          "name": "value",
          "type": "text",
          "primaryKey": false,
          "notNull": true
        },
        "expires_at": {
          "name": "expires_at",
          "type": "timestamp",
          "primaryKey": false,
          "notNull": true
        },
        "created_at": {
          "name": "created_at",
          "type": "timestamp",
          "primaryKey": false,
          "notNull": false
        },
        "updated_at": {
          "name": "updated_at",
          "type": "timestamp",
          "primaryKey": false,
          "notNull": false
        }
      },
      "indexes": {},
      "foreignKeys": {},
      "compositePrimaryKeys": {},
      "uniqueConstraints": {},
      "policies": {},
      "checkConstraints": {},
      "isRLSEnabled": false
    }
  },
  "enums": {},
  "schemas": {},
  "sequences": {},
  "roles": {},
  "policies": {},
  "views": {},
  "_meta": {
    "columns": {},
    "schemas": {},
    "tables": {}
  }
}